pir_processing/__init__.py
pir_processing/__main__.py
pir_processing/logger.py
pir_processing/pir.py
pir_processing/services.py
pir_processing/utils/__init__.py
pir_processing-0.0.8.dist-info/LICENSE.md
pir_processing-0.0.8.dist-info/METADATA
pir_processing-0.0.8.dist-info/WHEEL
pir_processing-0.0.8.dist-info/RECORD
