Metadata-Version: 2.1
Name: pir-processing
Version: 0.0.8
Summary: Python tools for processing ARTA's PIR file format
Home-page: https://github.com/pupkinivan/pir-processing
License: MIT
Keywords: audio,ARTA
Author: Ivan Pupkin
Author-email: ipupkin@untref.edu.ar
Requires-Python: >=3.8,<4.0
Classifier: License :: OSI Approved :: MIT License
Classifier: Programming Language :: Python :: 3
Classifier: Programming Language :: Python :: 3.8
Classifier: Programming Language :: Python :: 3.9
Classifier: Programming Language :: Python :: 3.10
Classifier: Programming Language :: Python :: 3.11
Requires-Dist: matplotlib (>=3.7.0,<4.0.0)
Requires-Dist: numpy (>=1.24.2,<2.0.0)
Requires-Dist: pandas (>=1.5.3,<2.0.0)
Project-URL: Repository, https://github.com/pupkinivan/pir-processing
